{
	"status":0,
	"message":[
		{
			"id":1,
			"title":"vivo X23 logo phone  8+128GB 移动联通电信全网通",
			"add_time":"2018-08-08 06:09:01",
			"content":"<p>vivo X23 logo phone  8+128GB 游戏手机 时尚紫 移动联通电信全网通 4G手机双卡双待 超大广角 发现更多美</p><img src='http://localhost:9000/upload/goods/page-1/1-1.jpg'><img src='http://localhost:9000/upload/goods/page-1/1-2.jpg'>",
			"goods_no":"SD3974359844",
			"sell_price":3498,
			"market_price":3498,
			"stock_quantity":99
		},
		{
			"id":2,
			"title":"惠普（HP） 香槟金 新一代四核i5/8G/256GPCI-E",
			"add_time":"2018-08-08 06:09:02",
			"content":"<p>旗舰店【新款】星14商务轻薄本笔记本电脑 金属超极本学生手提办公商用窄边框独显 香槟金 新一代四核i5/8G/256GPCI-E</p><img src='http://localhost:9000/upload/goods/page-1/2-1.jpg'><img src='http://localhost:9000/upload/goods/page-1/2-3.jpg'>",
			"goods_no":"SD3974359866",
			"sell_price":5299,
			"market_price":5299,
			"stock_quantity":99
		},
		{
			"id":3,
			"title":"ROG游戏手机 8GB+128GB 骁龙845 液冷散热 全面屏 全网通4G双卡双待",
			"add_time":"2018-08-08 06:09:03",
			"content":"<p>ROG游戏手机 8GB+128GB 骁龙845 液冷散热 全面屏 全网通4G双卡双待</p><img src='http://localhost:9000/upload/goods/page-1/3-1.jpg'><img src='http://localhost:9000/upload/goods/page-1/3-4.jpg'>",
			"goods_no":"SD3974569844",
			"sell_price":5999,
			"market_price":5999,
			"stock_quantity":0
		},
		{
			"id":4,
			"title":"佳能（Canon）EOS 750D 单反套机",
			"add_time":"2018-08-08 06:10:01",
			"content":"<p>佳能（Canon）EOS 750D 单反套机  (EF-S 18-55mm f/3.5-5.6 IS STM镜头) </p><img src='http://localhost:9000/upload/goods/page-2/4-1.jpg'><img src='http://localhost:9000/upload/goods/page-2/4-5.jpg'>",
			"goods_no":"SD3939359844",
			"sell_price":3979,
			"market_price":3999,
			"stock_quantity":9
		},
		{
			"id":5,
			"title":"升特便携锂电池电动滑板车 48V黑/前后减震/油碟刹/续航80-100KM",
			"add_time":"2018-08-08 06:11:01",
			"content":"<p>升特便携锂电池电动滑板车成人男女可折叠代步车两轮小型迷你电动车代驾电动自行车电瓶踏板车 48V黑/前后减震/油碟刹/续航80-100KM</p><img src='http://localhost:9000/upload/goods/page-2/5-1.jpg'><img src='http://localhost:9000/upload/goods/page-2/5-6.jpg'>",
			"goods_no":"SD3976529844",
			"sell_price":3280,
			"market_price":3398,
			"stock_quantity":69
		}
	]
}